{
  "success": true,
  "results": [
    {
      "bbox": [
        50,
        50,
        1650,
        150
      ],
      "confidence": 0.95,
      "class": "title",
      "class_id": 0,
      "text": "Document Title (Dummy)",
      "page": 1,
      "image_path": "/home/gwsgs/work_space/paperterrace/test_page.png"
    },
    {
      "bbox": [
        50,
        200,
        825,
        400
      ],
      "confidence": 0.88,
      "class": "text",
      "class_id": 2,
      "text": "Left column text content (Dummy)",
      "page": 1,
      "image_path": "/home/gwsgs/work_space/paperterrace/test_page.png"
    },
    {
      "bbox": [
        875,
        200,
        1650,
        400
      ],
      "confidence": 0.87,
      "class": "text",
      "class_id": 2,
      "text": "Right column text content (Dummy)",
      "page": 1,
      "image_path": "/home/gwsgs/work_space/paperterrace/test_page.png"
    },
    {
      "bbox": [
        50,
        450,
        1650,
        650
      ],
      "confidence": 0.92,
      "class": "table",
      "class_id": 8,
      "text": "Table content (Dummy)",
      "page": 1,
      "image_path": "/home/gwsgs/work_space/paperterrace/test_page.png"
    },
    {
      "bbox": [
        50,
        700,
        1650,
        2100
      ],
      "confidence": 0.85,
      "class": "text",
      "class_id": 2,
      "text": "Bottom text content (Dummy)",
      "page": 1,
      "image_path": "/home/gwsgs/work_space/paperterrace/test_page.png"
    }
  ],
  "processing_time": 2.862098455429077,
  "message": null
}